fastgame/__init__.py
fastgame/widget/__init__.py
fastgame-1.3.0.dist-info/LICENSE
fastgame-1.3.0.dist-info/METADATA
fastgame-1.3.0.dist-info/WHEEL
fastgame-1.3.0.dist-info/top_level.txt
fastgame-1.3.0.dist-info/RECORD
