Metadata-Version: 2.1
Name: fastgame
Version: 1.3.0
Summary: Fastgame是一个帮助你快速构建游戏或简单的GUI界面的python第三方库。
Home-page: UNKNOWN
Author: stripe-python
Author-email: 13513519246@139.com
Maintainer: stripe-python
Maintainer-email: 13513519246@139.com
License: UNKNOWN
Platform: UNKNOWN
Classifier: Programming Language :: Python :: 3
Classifier: License :: OSI Approved :: MIT License
Classifier: Operating System :: OS Independent
Requires-Python: >=3.6
Requires-Dist: pygame (>=2.1.0)
Requires-Dist: arrow
Requires-Dist: opencv-python
Requires-Dist: tqdm
Requires-Dist: pillow
